eyedrop/__init__.py
eyedrop/docs/__init__.py
eyedrop/src/__init__.py
eyedrop/test/__init__.py
eyedrop/test/unit_test/__init__.py
eyedrop/test/unit_test/test_everything.py
eyedrop-0.0.0a0.dist-info/LICENSE
eyedrop-0.0.0a0.dist-info/METADATA
eyedrop-0.0.0a0.dist-info/WHEEL
eyedrop-0.0.0a0.dist-info/top_level.txt
eyedrop-0.0.0a0.dist-info/RECORD
