Metadata-Version: 2.1
Name: eyedrop
Version: 0.0.0a0
Summary: UNKNOWN
Home-page: https://github.com/lumikapp/eyedrop/
Author: Lumik
Author-email: open_source@lumik.app
License: MIT
Platform: UNKNOWN
Classifier: License :: OSI Approved :: MIT License
Classifier: Programming Language :: Python :: 3
Classifier: Programming Language :: Python :: 3.6
Classifier: Programming Language :: Python :: 3.7
Classifier: Programming Language :: Python :: 3.8
Classifier: Programming Language :: Python :: 3.9
